kraken_g_api/kraken_bigquery.py
kraken_g_api/kraken_firestore.py
kraken_g_api/kraken_storage.py
kraken_g_api/kraken_task.py
kraken_g_api-0.0.1.dist-info/LICENSE.txt
kraken_g_api-0.0.1.dist-info/METADATA
kraken_g_api-0.0.1.dist-info/WHEEL
kraken_g_api-0.0.1.dist-info/top_level.txt
kraken_g_api-0.0.1.dist-info/RECORD
