Metadata-Version: 2.1
Name: kraken-g-api
Version: 0.0.1
Summary: Kraken g api
Home-page: https://github.com/tactik8/kraken_gstorage
Author: Tactik8
Author-email: info@tactik8.com
License: MIT
Platform: UNKNOWN
Classifier: License :: OSI Approved :: MIT License
Classifier: Programming Language :: Python :: 3
Classifier: Programming Language :: Python :: 3.8
Requires-Dist: flatten-dict
Requires-Dist: firebase-admin
Requires-Dist: google-cloud-storage
Requires-Dist: google-cloud-bigquery
Requires-Dist: google-cloud-tasks
